AUTHORS.rst
CONTRIBUTING.rst
HISTORY.rst
MANIFEST.in
README.md
setup.cfg
setup.py
docs/Makefile
docs/authors.rst
docs/conf.py
docs/contributing.rst
docs/history.rst
docs/index.rst
docs/installation.rst
docs/make.bat
docs/readme.rst
docs/usage.rst
leylab_pipelines/Join.py
leylab_pipelines/Utils.py
leylab_pipelines/__init__.py
leylab_pipelines/leylab_pipelines.py
leylab_pipelines.egg-info/PKG-INFO
leylab_pipelines.egg-info/SOURCES.txt
leylab_pipelines.egg-info/dependency_links.txt
leylab_pipelines.egg-info/not-zip-safe
leylab_pipelines.egg-info/requires.txt
leylab_pipelines.egg-info/top_level.txt
leylab_pipelines/DB/Acc2TaxID.py
leylab_pipelines/DB/Convert.py
leylab_pipelines/DB/EggNOG.py
leylab_pipelines/DB/TaxID2Lin.py
leylab_pipelines/DB/TaxID2LinTbl.py
leylab_pipelines/TECAN/Dilute.py
leylab_pipelines/TECAN/Fluent.py
leylab_pipelines/TECAN/Map2Robot.py
leylab_pipelines/TECAN/QPCR.py
leylab_pipelines/TECAN/__init__.py
scripts/LLP
scripts/LLP-DB
scripts/TECAN
scripts/dilute.py
scripts/map2robot.py
scripts/qPCR_setup.py
tests/.DS_Store
tests/._.DS_Store
tests/__init__.py
tests/test_Convert.py
tests/test_Dilute.py
tests/test_Fluent.py
tests/test_Map2Robot.py
tests/test_Utils.py
tests/test_leylab_pipelines.py
tests/test_qPCR_setup.py
tests/data/.DS_Store
tests/data/._.DS_Store
tests/data/._basic_384well.txt
tests/data/._basic_96well.txt
tests/data/._mapping_file_fecal_stability.txt
tests/data/accessions.txt
tests/data/accessions_col3.gz
tests/data/accessions_col3.txt
tests/data/basic_384well.txt
tests/data/basic_96well.txt
tests/data/conc_file1.txt
tests/data/conc_file2.txt
tests/data/mapping_file_fecal_stability.txt
tests/data/multi_dispense.gwl
tests/data/nucl_gss.acc2taxid.gz
tests/data/nucl_wg.acc2taxid
tests/data/plate_reader_std_curve.xlsx
tests/data/reagent_dispense.gwl
tests/data/qPCR_setup/._qPCR_Zach_plate1.csv
tests/data/qPCR_setup/._qPCR_Zach_plate1.xlsx
tests/data/qPCR_setup/._qPCR_Zach_plate1_original.xlsx
tests/data/qPCR_setup/._qPCR_Zach_plate2.csv
tests/data/qPCR_setup/._~$qPCR_Zach_plate1.xlsx
tests/data/qPCR_setup/qPCR_Zach_plate1.csv
tests/data/qPCR_setup/qPCR_Zach_plate1.xlsx
tests/data/qPCR_setup/qPCR_Zach_plate1_original.xlsx
tests/data/qPCR_setup/qPCR_Zach_plate2.csv
