Metadata-Version: 1.1
Name: leylab-pipelines
Version: 0.2.1
Summary: General bioinformatic pipelines associated with the Ley Lab at the MPI in Tuebingen
Home-page: https://github.com/leylabmpi/leylab_pipelines
Author: Nick Youngblut
Author-email: leylabmpi@gmail.com
License: MIT license
Keywords: leylab_pipelines
Platform: UNKNOWN
Classifier: Programming Language :: Python :: 2
Classifier: Programming Language :: Python :: 2.7
Classifier: Programming Language :: Python :: 3
Classifier: Programming Language :: Python :: 3.3
Classifier: Programming Language :: Python :: 3.4
Classifier: Programming Language :: Python :: 3.5
